google/cloud/tpu/__init__.py
google/cloud/tpu/gapic_version.py
google/cloud/tpu/py.typed
google/cloud/tpu_v1/__init__.py
google/cloud/tpu_v1/gapic_metadata.json
google/cloud/tpu_v1/gapic_version.py
google/cloud/tpu_v1/py.typed
google/cloud/tpu_v1/services/__init__.py
google/cloud/tpu_v1/services/tpu/__init__.py
google/cloud/tpu_v1/services/tpu/async_client.py
google/cloud/tpu_v1/services/tpu/client.py
google/cloud/tpu_v1/services/tpu/pagers.py
google/cloud/tpu_v1/services/tpu/transports/__init__.py
google/cloud/tpu_v1/services/tpu/transports/base.py
google/cloud/tpu_v1/services/tpu/transports/grpc.py
google/cloud/tpu_v1/services/tpu/transports/grpc_asyncio.py
google/cloud/tpu_v1/types/__init__.py
google/cloud/tpu_v1/types/cloud_tpu.py
google/cloud/tpu_v2/__init__.py
google/cloud/tpu_v2/gapic_metadata.json
google/cloud/tpu_v2/gapic_version.py
google/cloud/tpu_v2/py.typed
google/cloud/tpu_v2/services/__init__.py
google/cloud/tpu_v2/services/tpu/__init__.py
google/cloud/tpu_v2/services/tpu/async_client.py
google/cloud/tpu_v2/services/tpu/client.py
google/cloud/tpu_v2/services/tpu/pagers.py
google/cloud/tpu_v2/services/tpu/transports/__init__.py
google/cloud/tpu_v2/services/tpu/transports/base.py
google/cloud/tpu_v2/services/tpu/transports/grpc.py
google/cloud/tpu_v2/services/tpu/transports/grpc_asyncio.py
google/cloud/tpu_v2/services/tpu/transports/rest.py
google/cloud/tpu_v2/services/tpu/transports/rest_base.py
google/cloud/tpu_v2/types/__init__.py
google/cloud/tpu_v2/types/cloud_tpu.py
google/cloud/tpu_v2alpha1/__init__.py
google/cloud/tpu_v2alpha1/gapic_metadata.json
google/cloud/tpu_v2alpha1/gapic_version.py
google/cloud/tpu_v2alpha1/py.typed
google/cloud/tpu_v2alpha1/services/__init__.py
google/cloud/tpu_v2alpha1/services/tpu/__init__.py
google/cloud/tpu_v2alpha1/services/tpu/async_client.py
google/cloud/tpu_v2alpha1/services/tpu/client.py
google/cloud/tpu_v2alpha1/services/tpu/pagers.py
google/cloud/tpu_v2alpha1/services/tpu/transports/__init__.py
google_cloud_tpu-1.24.0.dist-info/licenses/LICENSE
google_cloud_tpu-1.24.0.dist-info/METADATA
google_cloud_tpu-1.24.0.dist-info/WHEEL
google_cloud_tpu-1.24.0.dist-info/top_level.txt
google_cloud_tpu-1.24.0.dist-info/RECORD
